Neuron/__init__.py
Neuron/perceptron.py
Neuron_package_khajaraouf-0.0.1.dist-info/LICENSE
Neuron_package_khajaraouf-0.0.1.dist-info/METADATA
Neuron_package_khajaraouf-0.0.1.dist-info/WHEEL
Neuron_package_khajaraouf-0.0.1.dist-info/top_level.txt
Neuron_package_khajaraouf-0.0.1.dist-info/RECORD
